datastar/__init__.py
datastar/_defaults.py
datastar/_version.py
datastar/connection.py
datastar/connection_registry.py
datastar/datastar_api.py
datastar/frog_platform.py
datastar/macro.py
datastar/project.py
datastar/py.typed
datastar/task.py
datastar/task_registry.py
datastar/connections/__init__.py
datastar/connections/delimited_connection.py
datastar/connections/excel_connection.py
datastar/connections/frog_model_connection.py
datastar/connections/opti_connection.py
datastar/connections/sandbox_connection.py
datastar/tasks/__init__.py
datastar/tasks/task_export.py
datastar/tasks/task_import.py
datastar/tasks/task_run_python.py
datastar/tasks/task_run_sql.py
datastar/tasks/task_start.py
ol_datastar-0.0.17.dist-info/METADATA
ol_datastar-0.0.17.dist-info/WHEEL
ol_datastar-0.0.17.dist-info/top_level.txt
ol_datastar-0.0.17.dist-info/RECORD
