Metadata-Version: 2.1
Name: ol_datastar
Version: 0.0.17
Summary: Helpful utilities for working with Datastar projects
Home-page: https://cosmicfrog.com
Author: Optilogic
License: MIT
Classifier: License :: OSI Approved :: MIT License
Classifier: Programming Language :: Python :: 3
Classifier: Operating System :: OS Independent
Requires-Python: >=3.11
Requires-Dist: optilogic >=2.13.0
Requires-Dist: PyJWT >=2.8.0
Requires-Dist: requests >=2.31.0
Requires-Dist: pandas >=2.0.0
Requires-Dist: SQLAlchemy >=2.0.0
